README.rst
setup.cfg
setup.py
hexagonit/__init__.py
hexagonit.virtualgallery.egg-info/PKG-INFO
hexagonit.virtualgallery.egg-info/SOURCES.txt
hexagonit.virtualgallery.egg-info/dependency_links.txt
hexagonit.virtualgallery.egg-info/entry_points.txt
hexagonit.virtualgallery.egg-info/namespace_packages.txt
hexagonit.virtualgallery.egg-info/not-zip-safe
hexagonit.virtualgallery.egg-info/requires.txt
hexagonit.virtualgallery.egg-info/top_level.txt
hexagonit/virtualgallery/__init__.py
hexagonit/virtualgallery/configure.zcml
hexagonit/virtualgallery/interfaces.py
hexagonit/virtualgallery/schema.py
hexagonit/virtualgallery/version.txt
hexagonit/virtualgallery/browser/__init__.py
hexagonit/virtualgallery/browser/configure.zcml
hexagonit/virtualgallery/browser/data.py
hexagonit/virtualgallery/browser/gallery.pt
hexagonit/virtualgallery/browser/gallery.py
hexagonit/virtualgallery/browser/interfaces.py
hexagonit/virtualgallery/browser/settings.py
hexagonit/virtualgallery/browser/resources/Virtual3DGallery.swf
hexagonit/virtualgallery/browser/resources/expressInstall.swf
hexagonit/virtualgallery/browser/resources/swfobject.js
hexagonit/virtualgallery/docs/CREDITS.rst
hexagonit/virtualgallery/docs/FUTURE.rst
hexagonit/virtualgallery/docs/HISTORY.rst
hexagonit/virtualgallery/docs/LICENSE.rst
hexagonit/virtualgallery/docs/Makefile
hexagonit/virtualgallery/docs/README.rst
hexagonit/virtualgallery/docs/conf.py
hexagonit/virtualgallery/docs/index.rst
hexagonit/virtualgallery/docs/images/screenshot.png
hexagonit/virtualgallery/locales/hexagonit.virtualgallery.pot
hexagonit/virtualgallery/locales/manual.pot
hexagonit/virtualgallery/locales/fi/LC_MESSAGES/hexagonit.virtualgallery.po
hexagonit/virtualgallery/locales/ru/LC_MESSAGES/hexagonit.virtualgallery.po
hexagonit/virtualgallery/locales/sl/LC_MESSAGES/hexagonit.virtualgallery.po
hexagonit/virtualgallery/profiles/default/actions.xml
hexagonit/virtualgallery/profiles/default/browserlayer.xml
hexagonit/virtualgallery/profiles/default/metadata.xml
hexagonit/virtualgallery/profiles/default/types/Folder.xml
hexagonit/virtualgallery/profiles/default/types/Topic.xml
hexagonit/virtualgallery/tests/__init__.py
hexagonit/virtualgallery/tests/base.py
hexagonit/virtualgallery/tests/test_data.py
hexagonit/virtualgallery/tests/test_functional.py
hexagonit/virtualgallery/tests/test_gallery_view.py
