Metadata-Version: 1.0
Name: hexagonit.virtualgallery
Version: 1.0
Summary: Virtual 3D image gallery for Plone
Home-page: UNKNOWN
Author: Hexagon IT
Author-email: oss@hexagonit.fi
License: BSD
Platform: UNKNOWN
Classifier: Framework :: Plone
Classifier: Programming Language :: Python
